README.md
pyproject.toml
setup.py
src/tech_ninja_tistory_api/__init__.py
src/tech_ninja_tistory_api/tistory_api.py
src/tech_ninja_tistory_api.egg-info/PKG-INFO
src/tech_ninja_tistory_api.egg-info/SOURCES.txt
src/tech_ninja_tistory_api.egg-info/dependency_links.txt
src/tech_ninja_tistory_api.egg-info/requires.txt
src/tech_ninja_tistory_api.egg-info/top_level.txt