Metadata-Version: 2.1
Name: tech-ninja-tistory-api
Version: 1.0.3
Summary: Tistory API Wrapper
Home-page: https://github.com/yscho03/tech-ninja-tistory-api
Author: yscho03
Author-email: yscho03.developer@gmail.com
License: UNKNOWN
Project-URL: Bug Tracker, https://github.com/yscho03/tech-ninja-tistory-api/issues
Platform: UNKNOWN
Classifier: Programming Language :: Python :: 3
Classifier: License :: OSI Approved :: MIT License
Classifier: Operating System :: OS Independent
Requires-Python: >=3.6
